saltext/cassandra/__init__.py
saltext/cassandra/version.py
saltext/cassandra/modules/__init__.py
saltext/cassandra/modules/cassandra_cql.py
saltext/cassandra/modules/cassandra_mod.py
saltext/cassandra/returners/__init__.py
saltext/cassandra/returners/cassandra_cql_return.py
saltext/cassandra/returners/cassandra_mod.py
saltext.cassandra-0.0.1.dist-info/LICENSE
saltext.cassandra-0.0.1.dist-info/METADATA
saltext.cassandra-0.0.1.dist-info/NOTICE
saltext.cassandra-0.0.1.dist-info/WHEEL
saltext.cassandra-0.0.1.dist-info/entry_points.txt
saltext.cassandra-0.0.1.dist-info/top_level.txt
saltext.cassandra-0.0.1.dist-info/RECORD
